MANIFEST.in
setup.py
webportfolio_extras/__init__.py
webportfolio_extras/audio.py
webportfolio_extras/newrelic_apm.py
webportfolio_extras/redis_data_structure.py
webportfolio_extras/rollbar_logger.py
webportfolio_extras/rq_worker.py
webportfolio_extras/taskman.py
webportfolio_extras.egg-info/PKG-INFO
webportfolio_extras.egg-info/SOURCES.txt
webportfolio_extras.egg-info/dependency_links.txt
webportfolio_extras.egg-info/pbr.json
webportfolio_extras.egg-info/requires.txt
webportfolio_extras.egg-info/top_level.txt